runai_model_streamer/libstreamer/lib/libstreamerazure.so
runai_model_streamer_azure/__init__.py
runai_model_streamer_azure/credentials/__init__.py
runai_model_streamer_azure/credentials/credentials.py
runai_model_streamer_azure/files/__init__.py
runai_model_streamer_azure/files/files.py
runai_model_streamer_azure/files/tests/__init__.py
runai_model_streamer_azure/files/tests/test_files.py
runai_model_streamer_azure_hari-0.0.1.dev3.dist-info/LICENSE
runai_model_streamer_azure_hari-0.0.1.dev3.dist-info/METADATA
runai_model_streamer_azure_hari-0.0.1.dev3.dist-info/WHEEL
runai_model_streamer_azure_hari-0.0.1.dev3.dist-info/top_level.txt
runai_model_streamer_azure_hari-0.0.1.dev3.dist-info/RECORD
