Metadata-Version: 2.1
Name: runai-model-streamer-azure-hari
Version: 0.0.1.dev3
Summary: UNKNOWN
Home-page: UNKNOWN
Author: UNKNOWN
Author-email: UNKNOWN
License: UNKNOWN
Platform: UNKNOWN
Requires-Dist: azure-identity
Requires-Dist: azure-storage-blob
